mediawiki_to_pdf/__init__.py
mediawiki_to_pdf/main.py
mediawiki_to_pdf/pdf.py
mediawiki_to_pdf/wsession.py
mediawiki_to_pdf-1.0.dist-info/licenses/LICENSE
mediawiki_to_pdf-1.0.dist-info/METADATA
mediawiki_to_pdf-1.0.dist-info/WHEEL
mediawiki_to_pdf-1.0.dist-info/entry_points.txt
mediawiki_to_pdf-1.0.dist-info/top_level.txt
mediawiki_to_pdf-1.0.dist-info/RECORD
