Metadata-Version: 2.4
Name: mediawiki-to-pdf
Version: 1.0
Summary: TBD
Author: Gerard
Author-email: gweatherby@uchc.edu
License: MIT
Project-URL: Homepage, https://github.com/NMRhub/mediawiki_to_pdf
Project-URL: Repository, https://github.com/NMRhub/mediawiki_to_pdf
Project-URL: Issues, https://github.com/NMRhub/mediawiki_to_pdf/issues
Project-URL: Changelog, https://github.com/NMRhub/mediawiki_to_pdf/releases
Requires-Python: >=3.10
License-File: LICENSE
Requires-Dist: pdfkit
Requires-Dist: pyyaml
Dynamic: license-file
